crypto_ws_api/__init__.py
crypto_ws_api/demo.py
crypto_ws_api/ws_api.toml.template
crypto_ws_api/ws_session.py
crypto_ws_api-2.1.6.dist-info/entry_points.txt
crypto_ws_api-2.1.6.dist-info/LICENSE.md
crypto_ws_api-2.1.6.dist-info/WHEEL
crypto_ws_api-2.1.6.dist-info/METADATA
crypto_ws_api-2.1.6.dist-info/RECORD
