Metadata-Version: 2.1
Name: crypto-ws-api
Version: 2.1.6
Summary: Crypto WS API connector for ASYNC requests
Author-email: Jerry Fedorenko <jerry.fedorenko@yahoo.com>
Requires-Python: >=3.10
Classifier: Programming Language :: Python :: 3
Classifier: Development Status :: 5 - Production/Stable
Classifier: License :: OSI Approved :: MIT License
Classifier: Operating System :: Unix
Classifier: Operating System :: Microsoft :: Windows
Classifier: Operating System :: MacOS
Requires-Dist: shortuuid~=1.0.13
Requires-Dist: platformdirs==4.5.0
Requires-Dist: toml~=0.10.2
Requires-Dist: websockets==16.0
Requires-Dist: ujson~=5.11.0
Requires-Dist: cryptography~=46.0.3
Project-URL: Source, https://github.com/DogsTailFarmer/crypto-ws-api
